Metadata-Version: 2.1
Name: odoo8-addon-website-slides
Version: 8.0.2.0.1
Summary: Share and Publish Videos, Presentations and Documents
Home-page: https://github.com/OCA/website
Author: Odoo SA, Incaser Informatica - Sergio Teruel, Odoo Community Association (OCA)
Author-email: support@odoo-community.org
License: LGPL-3
Platform: UNKNOWN
Classifier: Programming Language :: Python
Classifier: Framework :: Odoo
Classifier: License :: OSI Approved :: GNU Lesser General Public License v3 (LGPLv3)
Requires-Python: ~=2.7
Requires-Dist: odoo (<9.0a,>=8.0a)
